{"initialAllocation": [{"app": "0", "module_name": "0_0", "id_resource": 24}, {"app": "0", "module_name": "0_0", "id_resource": 26}, {"app": "0", "module_name": "0_0", "id_resource": 99}, {"app": "0", "module_name": "0_0", "id_resource": 104}, {"app": "0", "module_name": "0_0", "id_resource": 136}, {"app": "0", "module_name": "0_1", "id_resource": 24}, {"app": "0", "module_name": "0_1", "id_resource": 26}, {"app": "0", "module_name": "0_1", "id_resource": 50}, {"app": "0", "module_name": "0_1", "id_resource": 99}, {"app": "0", "module_name": "0_1", "id_resource": 104}, {"app": "0", "module_name": "0_1", "id_resource": 136}, {"app": "0", "module_name": "0_2", "id_resource": 24}, {"app": "0", "module_name": "0_2", "id_resource": 26}, {"app": "0", "module_name": "0_2", "id_resource": 50}, {"app": "0", "module_name": "0_2", "id_resource": 99}, {"app": "0", "module_name": "0_2", "id_resource": 104}, {"app": "0", "module_name": "0_2", "id_resource": 136}, {"app": "0", "module_name": "0_3", "id_resource": 24}, {"app": "0", "module_name": "0_3", "id_resource": 26}, {"app": "0", "module_name": "0_3", "id_resource": 50}, {"app": "0", "module_name": "0_3", "id_resource": 99}, {"app": "0", "module_name": "0_3", "id_resource": 104}, {"app": "0", "module_name": "0_3", "id_resource": 136}, {"app": "1", "module_name": "1_4", "id_resource": 20}, {"app": "1", "module_name": "1_5", "id_resource": 112}, {"app": "1", "module_name": "1_6", "id_resource": 151}, {"app": "1", "module_name": "1_7", "id_resource": 20}, {"app": "1", "module_name": "1_8", "id_resource": 151}, {"app": "1", "module_name": "1_9", "id_resource": 151}, {"app": "2", "module_name": "2_10", "id_resource": 21}, {"app": "2", "module_name": "2_10", "id_resource": 28}, {"app": "2", "module_name": "2_10", "id_resource": 89}, {"app": "2", "module_name": "2_11", "id_resource": 89}, {"app": "2", "module_name": "2_11", "id_resource": 97}, {"app": "2", "module_name": "2_11", "id_resource": 136}, {"app": "2", "module_name": "2_12", "id_resource": 89}, {"app": "2", "module_name": "2_12", "id_resource": 97}, {"app": "2", "module_name": "2_12", "id_resource": 136}, {"app": "2", "module_name": "2_13", "id_resource": 89}, {"app": "2", "module_name": "2_13", "id_resource": 97}, {"app": "2", "module_name": "2_13", "id_resource": 136}, {"app": "3", "module_name": "3_14", "id_resource": 23}, {"app": "3", "module_name": "3_14", "id_resource": 62}, {"app": "3", "module_name": "3_14", "id_resource": 63}, {"app": "3", "module_name": "3_14", "id_resource": 93}, {"app": "3", "module_name": "3_15", "id_resource": 93}, {"app": "3", "module_name": "3_15", "id_resource": 151}, {"app": "3", "module_name": "3_15", "id_resource": 194}, {"app": "3", "module_name": "3_15", "id_resource": 195}, {"app": "3", "module_name": "3_16", "id_resource": 112}, {"app": "3", "module_name": "3_16", "id_resource": 151}, {"app": "3", "module_name": "3_16", "id_resource": 165}, {"app": "3", "module_name": "3_16", "id_resource": 174}, {"app": "3", "module_name": "3_17", "id_resource": 93}, {"app": "3", "module_name": "3_17", "id_resource": 99}, {"app": "3", "module_name": "3_17", "id_resource": 112}, {"app": "3", "module_name": "3_18", "id_resource": 93}, {"app": "3", "module_name": "3_18", "id_resource": 151}, {"app": "3", "module_name": "3_18", "id_resource": 165}, {"app": "3", "module_name": "3_18", "id_resource": 174}, {"app": "3", "module_name": "3_19", "id_resource": 23}, {"app": "3", "module_name": "3_19", "id_resource": 62}, {"app": "3", "module_name": "3_19", "id_resource": 93}, {"app": "3", "module_name": "3_19", "id_resource": 112}, {"app": "3", "module_name": "3_20", "id_resource": 23}, {"app": "3", "module_name": "3_20", "id_resource": 62}, {"app": "3", "module_name": "3_20", "id_resource": 93}, {"app": "3", "module_name": "3_20", "id_resource": 112}, {"app": "4", "module_name": "4_21", "id_resource": 21}, {"app": "4", "module_name": "4_21", "id_resource": 24}, {"app": "4", "module_name": "4_21", "id_resource": 25}, {"app": "4", "module_name": "4_21", "id_resource": 26}, {"app": "4", "module_name": "4_21", "id_resource": 28}, {"app": "4", "module_name": "4_21", "id_resource": 53}, {"app": "4", "module_name": "4_22", "id_resource": 21}, {"app": "4", "module_name": "4_22", "id_resource": 24}, {"app": "4", "module_name": "4_22", "id_resource": 25}, {"app": "4", "module_name": "4_22", "id_resource": 26}, {"app": "4", "module_name": "4_22", "id_resource": 28}, {"app": "4", "module_name": "4_22", "id_resource": 53}, {"app": "4", "module_name": "4_23", "id_resource": 21}, {"app": "4", "module_name": "4_23", "id_resource": 24}, {"app": "4", "module_name": "4_23", "id_resource": 25}, {"app": "4", "module_name": "4_23", "id_resource": 28}, {"app": "4", "module_name": "4_23", "id_resource": 53}, {"app": "4", "module_name": "4_23", "id_resource": 162}, {"app": "4", "module_name": "4_24", "id_resource": 97}, {"app": "4", "module_name": "4_24", "id_resource": 152}, {"app": "4", "module_name": "4_24", "id_resource": 159}, {"app": "4", "module_name": "4_24", "id_resource": 162}, {"app": "4", "module_name": "4_25", "id_resource": 21}, {"app": "4", "module_name": "4_25", "id_resource": 25}, {"app": "4", "module_name": "4_25", "id_resource": 28}, {"app": "4", "module_name": "4_25", "id_resource": 53}, {"app": "4", "module_name": "4_25", "id_resource": 159}, {"app": "4", "module_name": "4_25", "id_resource": 162}, {"app": "4", "module_name": "4_26", "id_resource": 21}, {"app": "4", "module_name": "4_26", "id_resource": 25}, {"app": "4", "module_name": "4_26", "id_resource": 28}, {"app": "4", "module_name": "4_26", "id_resource": 53}, {"app": "4", "module_name": "4_26", "id_resource": 162}, {"app": "4", "module_name": "4_26", "id_resource": 224}, {"app": "4", "module_name": "4_27", "id_resource": 21}, {"app": "4", "module_name": "4_27", "id_resource": 25}, {"app": "4", "module_name": "4_27", "id_resource": 28}, {"app": "4", "module_name": "4_27", "id_resource": 53}, {"app": "4", "module_name": "4_27", "id_resource": 162}, {"app": "4", "module_name": "4_27", "id_resource": 218}, {"app": "5", "module_name": "5_28", "id_resource": 22}, {"app": "5", "module_name": "5_29", "id_resource": 97}, {"app": "5", "module_name": "5_30", "id_resource": 22}, {"app": "5", "module_name": "5_31", "id_resource": 97}, {"app": "5", "module_name": "5_32", "id_resource": 22}, {"app": "7", "module_name": "7_37", "id_resource": 22}, {"app": "7", "module_name": "7_38", "id_resource": 22}, {"app": "7", "module_name": "7_39", "id_resource": 22}, {"app": "7", "module_name": "7_40", "id_resource": 22}, {"app": "8", "module_name": "8_41", "id_resource": 20}, {"app": "8", "module_name": "8_41", "id_resource": 27}, {"app": "8", "module_name": "8_41", "id_resource": 93}, {"app": "8", "module_name": "8_42", "id_resource": 20}, {"app": "8", "module_name": "8_42", "id_resource": 27}, {"app": "8", "module_name": "8_42", "id_resource": 97}, {"app": "8", "module_name": "8_42", "id_resource": 99}, {"app": "8", "module_name": "8_43", "id_resource": 20}, {"app": "8", "module_name": "8_43", "id_resource": 27}, {"app": "8", "module_name": "8_43", "id_resource": 93}, {"app": "8", "module_name": "8_44", "id_resource": 20}, {"app": "8", "module_name": "8_44", "id_resource": 27}, {"app": "8", "module_name": "8_44", "id_resource": 162}, {"app": "8", "module_name": "8_45", "id_resource": 20}, {"app": "8", "module_name": "8_45", "id_resource": 27}, {"app": "8", "module_name": "8_45", "id_resource": 162}, {"app": "8", "module_name": "8_45", "id_resource": 193}, {"app": "9", "module_name": "9_46", "id_resource": 89}, {"app": "9", "module_name": "9_47", "id_resource": 96}, {"app": "9", "module_name": "9_48", "id_resource": 110}, {"app": "9", "module_name": "9_49", "id_resource": 96}, {"app": "11", "module_name": "11_55", "id_resource": 104}, {"app": "11", "module_name": "11_55", "id_resource": 110}, {"app": "11", "module_name": "11_56", "id_resource": 50}, {"app": "11", "module_name": "11_56", "id_resource": 91}, {"app": "11", "module_name": "11_57", "id_resource": 50}, {"app": "11", "module_name": "11_57", "id_resource": 91}, {"app": "12", "module_name": "12_58", "id_resource": 94}, {"app": "12", "module_name": "12_59", "id_resource": 94}, {"app": "12", "module_name": "12_60", "id_resource": 94}, {"app": "12", "module_name": "12_61", "id_resource": 170}, {"app": "13", "module_name": "13_62", "id_resource": 89}, {"app": "13", "module_name": "13_62", "id_resource": 94}, {"app": "13", "module_name": "13_63", "id_resource": 89}, {"app": "13", "module_name": "13_63", "id_resource": 94}, {"app": "16", "module_name": "16_74", "id_resource": 95}, {"app": "16", "module_name": "16_74", "id_resource": 127}, {"app": "16", "module_name": "16_74", "id_resource": 136}, {"app": "16", "module_name": "16_75", "id_resource": 91}, {"app": "16", "module_name": "16_75", "id_resource": 95}, {"app": "16", "module_name": "16_75", "id_resource": 126}, {"app": "16", "module_name": "16_75", "id_resource": 127}, {"app": "16", "module_name": "16_76", "id_resource": 91}, {"app": "16", "module_name": "16_76", "id_resource": 95}, {"app": "16", "module_name": "16_76", "id_resource": 126}, {"app": "16", "module_name": "16_76", "id_resource": 127}, {"app": "16", "module_name": "16_77", "id_resource": 91}, {"app": "16", "module_name": "16_77", "id_resource": 95}, {"app": "16", "module_name": "16_77", "id_resource": 127}, {"app": "17", "module_name": "17_78", "id_resource": 53}, {"app": "17", "module_name": "17_79", "id_resource": 54}, {"app": "18", "module_name": "18_80", "id_resource": 23}, {"app": "18", "module_name": "18_80", "id_resource": 62}, {"app": "18", "module_name": "18_80", "id_resource": 63}, {"app": "18", "module_name": "18_81", "id_resource": 23}, {"app": "18", "module_name": "18_81", "id_resource": 62}, {"app": "18", "module_name": "18_81", "id_resource": 63}, {"app": "18", "module_name": "18_82", "id_resource": 23}, {"app": "18", "module_name": "18_82", "id_resource": 62}, {"app": "18", "module_name": "18_82", "id_resource": 63}, {"app": "18", "module_name": "18_82", "id_resource": 112}, {"app": "18", "module_name": "18_83", "id_resource": 23}, {"app": "18", "module_name": "18_83", "id_resource": 62}, {"app": "18", "module_name": "18_83", "id_resource": 63}, {"app": "18", "module_name": "18_83", "id_resource": 170}, {"app": "19", "module_name": "19_84", "id_resource": 104}, {"app": "19", "module_name": "19_84", "id_resource": 110}, {"app": "19", "module_name": "19_85", "id_resource": 110}, {"app": "19", "module_name": "19_85", "id_resource": 196}, {"app": "19", "module_name": "19_86", "id_resource": 110}, {"app": "19", "module_name": "19_86", "id_resource": 174}, {"app": "19", "module_name": "19_87", "id_resource": 110}, {"app": "19", "module_name": "19_87", "id_resource": 174}, {"app": "19", "module_name": "19_88", "id_resource": 104}, {"app": "19", "module_name": "19_88", "id_resource": 110}, {"app": "19", "module_name": "19_89", "id_resource": 104}, {"app": "19", "module_name": "19_89", "id_resource": 110}]}